rompy_xbeach/__init__.py
rompy_xbeach/boundary.py
rompy_xbeach/cli.py
rompy_xbeach/config.py
rompy_xbeach/data.py
rompy_xbeach/forcing.py
rompy_xbeach/grid.py
rompy_xbeach/interpolate.py
rompy_xbeach/source.py
rompy_xbeach/types.py
rompy_xbeach/components/__init__.py
rompy_xbeach/components/boundary.py
rompy_xbeach/components/forcing.py
rompy_xbeach/templates/base/{{runtime.run_id}}/params.txt
rompy_xbeach-0.2.0.dist-info/licenses/AUTHORS.rst
rompy_xbeach-0.2.0.dist-info/licenses/LICENSE
rompy_xbeach-0.2.0.dist-info/METADATA
rompy_xbeach-0.2.0.dist-info/WHEEL
rompy_xbeach-0.2.0.dist-info/entry_points.txt
rompy_xbeach-0.2.0.dist-info/top_level.txt
rompy_xbeach-0.2.0.dist-info/RECORD
