Metadata-Version: 2.4
Name: rompy_xbeach
Version: 0.2.0
Summary: Rompy Xbeach Config package.
Author-email: Rompy Developers <developers@rompy.com>
Maintainer-email: Rompy Developers <developers@rompy.com>
License: BSD 3-Clause License
Project-URL: bugs, https://github.com/rom-py/rompy_xbeach/issues
Project-URL: changelog, https://github.com/rom-py/rompy_xbeach/blob/master/changelog.md
Project-URL: homepage, https://github.com/rom-py/rompy_xbeach
License-File: LICENSE
License-File: AUTHORS.rst
Requires-Dist: rioxarray
Requires-Dist: rompy==0.3.1
Requires-Dist: oceantide
Requires-Dist: typer
Provides-Extra: extra
Requires-Dist: rompy-binary-datasources; extra == "extra"
Provides-Extra: dev
Requires-Dist: coverage; extra == "dev"
Requires-Dist: mypy; extra == "dev"
Requires-Dist: pytest; extra == "dev"
Requires-Dist: ruff; extra == "dev"
Dynamic: license-file
